LICENSE
LICENSE_ASSETS.md
MANIFEST.in
README.md
pyproject.toml
setup.py
eden_grasp_gen.egg-info/PKG-INFO
eden_grasp_gen.egg-info/SOURCES.txt
eden_grasp_gen.egg-info/dependency_links.txt
eden_grasp_gen.egg-info/entry_points.txt
eden_grasp_gen.egg-info/requires.txt
eden_grasp_gen.egg-info/top_level.txt
grasp_gen/__init__.py
grasp_gen/_main.py
grasp_gen/grasp_server.py
grasp_gen/metrics.py
grasp_gen/robot.py
grasp_gen/assets/figs/franka.png
grasp_gen/assets/figs/lego_jhh.png
grasp_gen/assets/figs/suction.png
grasp_gen/assets/franka/franka_panda.urdf
grasp_gen/assets/franka/meshes/collision/finger.obj
grasp_gen/assets/franka/meshes/collision/hand.obj
grasp_gen/assets/franka/meshes/collision/link0.obj
grasp_gen/assets/franka/meshes/collision/link1.obj
grasp_gen/assets/franka/meshes/collision/link2.obj
grasp_gen/assets/franka/meshes/collision/link3.obj
grasp_gen/assets/franka/meshes/collision/link4.obj
grasp_gen/assets/franka/meshes/collision/link5.obj
grasp_gen/assets/franka/meshes/collision/link6.obj
grasp_gen/assets/franka/meshes/collision/link7.obj
grasp_gen/assets/franka/meshes/visual/finger.dae
grasp_gen/assets/franka/meshes/visual/hand.dae
grasp_gen/assets/franka/meshes/visual/link0.dae
grasp_gen/assets/franka/meshes/visual/link1.dae
grasp_gen/assets/franka/meshes/visual/link2.dae
grasp_gen/assets/franka/meshes/visual/link3.dae
grasp_gen/assets/franka/meshes/visual/link4.dae
grasp_gen/assets/franka/meshes/visual/link5.dae
grasp_gen/assets/franka/meshes/visual/link6.dae
grasp_gen/assets/franka/meshes/visual/link7.dae
grasp_gen/assets/panda_gripper/finger.stl
grasp_gen/assets/panda_gripper/hand.stl
grasp_gen/assets/robotiq/robotiq_140_collision.obj
grasp_gen/assets/suction/suction_cup.obj
grasp_gen/config/grippers/franka_panda.py
grasp_gen/config/grippers/franka_panda.yaml
grasp_gen/config/grippers/robotiq_2f_140.py
grasp_gen/config/grippers/robotiq_2f_140.yaml
grasp_gen/config/grippers/robotiq_2f_85.yaml
grasp_gen/config/grippers/single_suction_cup_30mm.py
grasp_gen/config/grippers/single_suction_cup_30mm.yaml
grasp_gen/dataset/dataset.py
grasp_gen/dataset/dataset_utils.py
grasp_gen/dataset/eval_utils.py
grasp_gen/dataset/exceptions.py
grasp_gen/dataset/image_utils.py
