Metadata-Version: 2.4
Name: eden_grasp_gen
Version: 0.1.2
Summary: A fork of GraspGen for EDEN project
Home-page: https://github.com/NVlabs/GraspGen
Author: Kashu Yamazaki
Author-email: Kashu Yamazaki <kyamazak@andrew.cmu.edu>
License: NVIDIA License
Classifier: Programming Language :: Python :: 3
Classifier: Topic :: Scientific/Engineering
Requires-Python: >=3.10
License-File: LICENSE
License-File: LICENSE_ASSETS.md
Requires-Dist: h5py
Requires-Dist: hydra-core
Requires-Dist: matplotlib
Requires-Dist: meshcat
Requires-Dist: numpy==1.26.4
Requires-Dist: webdataset
Requires-Dist: scikit-learn
Requires-Dist: scipy
Requires-Dist: tensorboard
Requires-Dist: trimesh==4.5.3
Requires-Dist: transformers
Requires-Dist: tensordict
Requires-Dist: diffusers==0.11.1
Requires-Dist: timm==1.0.15
Requires-Dist: huggingface-hub==0.25.2
Requires-Dist: PyOpenGL==3.1.5
Requires-Dist: addict
Requires-Dist: spconv-cu126
Requires-Dist: yapf==0.40.1
Requires-Dist: tensorboardx
Requires-Dist: sharedarray
Requires-Dist: torch-geometric
Requires-Dist: yourdfpy==0.0.56
Dynamic: author
Dynamic: home-page
Dynamic: license-file
Dynamic: requires-python
